e_filetypes_py/__init__.py
e_filetypes_py/efiletypes.py
e_filetypes_py/helpers.py
e_filetypes_py/library/words.txt
e_filetypes_py-3.0.0.dist-info/WHEEL
e_filetypes_py-3.0.0.dist-info/METADATA
e_filetypes_py-3.0.0.dist-info/RECORD
