Metadata-Version: 2.1
Name: e-filetypes-py
Version: 3.0.0
Summary: The E-FileTypes-Py library allows you to integrate with E-FileTypes using any Python application.
Author-email: Wamy <davidisadev@gmail.com>
Requires-Python: >=3.8
Classifier: Programming Language :: Python :: 3
Classifier: License :: OSI Approved :: MIT License
Classifier: Operating System :: OS Independent
Requires-Dist: cryptography
Project-URL: Bug Tracker, https://github.com/E-FileTypes/e-filetypes-py/issues
Project-URL: Homepage, https://github.com/E-FileTypes/e-filetypes-py
